logram/__init__.py
logram/handlers.py
logram-0.0.3.dist-info/LICENSE
logram-0.0.3.dist-info/METADATA
logram-0.0.3.dist-info/WHEEL
logram-0.0.3.dist-info/top_level.txt
logram-0.0.3.dist-info/RECORD
