Metadata-Version: 2.1
Name: logram
Version: 0.0.3
Summary: Send logging messages to different channels (only Telegram for now)
Home-page: https://github.com/mutcato/logram
Author: Mutlucan Tokat
Author-email: mtokat1@gmail.com
License: UNKNOWN
Platform: UNKNOWN
Classifier: Programming Language :: Python :: 3
Classifier: License :: OSI Approved :: MIT License
Classifier: Operating System :: OS Independent
Requires-Python: >=3.7
License-File: LICENSE
Requires-Dist: python-telegram-bot (>=13.7)
